structifytext/__init__.py
structifytext/parser.py
structifytext-0.2.1.dist-info/DESCRIPTION.rst
structifytext-0.2.1.dist-info/LICENSE.txt
structifytext-0.2.1.dist-info/METADATA
structifytext-0.2.1.dist-info/metadata.json
structifytext-0.2.1.dist-info/RECORD
structifytext-0.2.1.dist-info/top_level.txt
structifytext-0.2.1.dist-info/WHEEL
