Metadata-Version: 2.0
Name: structifytext
Version: 0.2.1
Summary: Structure semi-structured text
Home-page: https://github.com/darinsikanic/structifytext
Author: Darin Sikanic
Author-email: darin.sikanic@gmail.com
License: Apache
Keywords: sructuretext structifytext structure text network cli parser
Platform: UNKNOWN
Classifier: Development Status :: 2 - Pre-Alpha
Classifier: Intended Audience :: Developers
Classifier: Intended Audience :: Telecommunications Industry
Classifier: License :: OSI Approved :: Apache Software License
Classifier: Operating System :: OS Independent
Classifier: Programming Language :: Python
Classifier: Programming Language :: Python :: 2.7
Classifier: Topic :: Software Development :: Libraries
Classifier: Topic :: Software Development :: Libraries :: Python Modules
Classifier: Topic :: System :: Networking
Requires-Dist: six
